xhtml2pdf/__init__.py
xhtml2pdf/charts.py
xhtml2pdf/context.py
xhtml2pdf/default.py
xhtml2pdf/document.py
xhtml2pdf/files.py
xhtml2pdf/paragraph.py
xhtml2pdf/parser.py
xhtml2pdf/pdf.py
xhtml2pdf/pisa.py
xhtml2pdf/reportlab_paragraph.py
xhtml2pdf/tables.py
xhtml2pdf/tags.py
xhtml2pdf/util.py
xhtml2pdf/wsgi.py
xhtml2pdf/xhtml2pdf_reportlab.py
xhtml2pdf/builders/__init__.py
xhtml2pdf/builders/signs.py
xhtml2pdf/builders/watermarks.py
xhtml2pdf/config/__init__.py
xhtml2pdf/config/httpconfig.py
xhtml2pdf/w3c/__init__.py
xhtml2pdf/w3c/css.py
xhtml2pdf/w3c/cssDOMElementInterface.py
xhtml2pdf/w3c/cssParser.py
xhtml2pdf/w3c/cssSpecial.py
xhtml2pdf-0.2.16.dist-info/AUTHORS.rst
xhtml2pdf-0.2.16.dist-info/LICENSE.txt
xhtml2pdf-0.2.16.dist-info/METADATA
xhtml2pdf-0.2.16.dist-info/WHEEL
xhtml2pdf-0.2.16.dist-info/entry_points.txt
xhtml2pdf-0.2.16.dist-info/top_level.txt
xhtml2pdf-0.2.16.dist-info/RECORD
