Metadata-Version: 2.1
Name: xhtml2pdf
Version: 0.2.16
Summary: PDF generator using HTML and CSS
Author-email: Dirk Holtwick <dirk.holtwick@gmail.com>
Maintainer-email: Luis Zarate <luisza14@gmail.com>, Timo Brembeck <opensource@timo.brembeck.email>
License: 
Project-URL: Repository, https://github.com/xhtml2pdf/xhtml2pdf
Project-URL: Bug tracker, https://github.com/xhtml2pdf/xhtml2pdf/issues
Project-URL: Documentation, https://xhtml2pdf.readthedocs.io/
Project-URL: Changelog, https://xhtml2pdf.readthedocs.io/en/latest/release-notes.html
Keywords: PDF,HTML,HTML,XML,CSS
Classifier: License :: OSI Approved :: Apache Software License
Classifier: Development Status :: 4 - Beta
Classifier: Environment :: Console
Classifier: Environment :: Other Environment
Classifier: Intended Audience :: Developers
Classifier: Intended Audience :: System Administrators
Classifier: Natural Language :: English
Classifier: Operating System :: OS Independent
Classifier: Programming Language :: Python :: 3
Classifier: Programming Language :: Python :: 3.8
Classifier: Programming Language :: Python :: 3.9
Classifier: Programming Language :: Python :: 3.10
Classifier: Programming Language :: Python :: 3.11
Classifier: Programming Language :: Python :: 3.12
Classifier: Topic :: Documentation
Classifier: Topic :: Multimedia
Classifier: Topic :: Office/Business
Classifier: Topic :: Printing
Classifier: Topic :: Text Processing
Classifier: Topic :: Text Processing :: Filters
Classifier: Topic :: Text Processing :: Fonts
Classifier: Topic :: Text Processing :: General
Classifier: Topic :: Text Processing :: Indexing
Classifier: Topic :: Text Processing :: Markup
Classifier: Topic :: Text Processing :: Markup :: HTML
Classifier: Topic :: Text Processing :: Markup :: XML
Classifier: Topic :: Utilities
Requires-Python: >=3.8
License-File: LICENSE.txt
License-File: AUTHORS.rst
Requires-Dist: arabic-reshaper>=3.0.0
Requires-Dist: html5lib>=1.1
Requires-Dist: Pillow>=8.1.1
Requires-Dist: pyHanko>=0.12.1
Requires-Dist: pyhanko-certvalidator>=0.19.5
Requires-Dist: pypdf>=3.1.0
Requires-Dist: python-bidi>=0.4.2
Requires-Dist: reportlab<5,>=4.0.4
Requires-Dist: svglib>=1.2.1
Provides-Extra: pycairo
Requires-Dist: reportlab[pycairo]<5,>=4.0.4; extra == "pycairo"
Provides-Extra: renderpm
Requires-Dist: reportlab[renderpm]<5,>=4.0.4; extra == "renderpm"
Provides-Extra: test
Requires-Dist: tomli>=2.0.1; python_version < "3.11" and extra == "test"
Requires-Dist: tox; extra == "test"
Requires-Dist: coverage>=5.3; extra == "test"
Provides-Extra: docs
Requires-Dist: sphinx>=6; extra == "docs"
Requires-Dist: sphinx-rtd-theme>=0.5.0; extra == "docs"
Provides-Extra: release
Requires-Dist: build; extra == "release"
Requires-Dist: twine; extra == "release"
